usermaven/__init__.py
usermaven/assets/images/logos/usermaven-logo-white.png
usermaven/assets/images/logos/usermaven-logo.png
usermaven/client.py
usermaven/consumer.py
usermaven/request.py
usermaven/settings.py
usermaven/test/__init__.py
usermaven/test/test_client.py
usermaven/test/test_consumer.py
usermaven/test/test_request.py
usermaven/test/test_utils.py
usermaven/utils.py
usermaven/version.py
usermaven-0.1.2.dist-info/LICENSE
usermaven-0.1.2.dist-info/WHEEL
usermaven-0.1.2.dist-info/METADATA
usermaven-0.1.2.dist-info/RECORD
