Metadata-Version: 2.1
Name: usermaven
Version: 0.1.2
Summary: 
Author: usermaven
Author-email: azhar@usermaven.com
Requires-Python: >=3.6,<4.0
Classifier: Programming Language :: Python :: 3
Classifier: Programming Language :: Python :: 3.6
Classifier: Programming Language :: Python :: 3.7
Classifier: Programming Language :: Python :: 3.8
Classifier: Programming Language :: Python :: 3.9
Classifier: Programming Language :: Python :: 3.10
Classifier: Programming Language :: Python :: 3.11
Requires-Dist: backoff (>=1.10.0,<2.0.0)
Requires-Dist: monotonic (>=1.5)
Requires-Dist: python-dateutil (>2.1)
Requires-Dist: requests (>=2.7,<3.0)
Requires-Dist: six (>=1.5)
